README.md
setup.py
wrapdll/__init__.py
wrapdll/wrapdll.py
wrapdll.egg-info/PKG-INFO
wrapdll.egg-info/SOURCES.txt
wrapdll.egg-info/dependency_links.txt
wrapdll.egg-info/top_level.txt
wrapdll/tests/__init__.py
wrapdll/tests/test_defaults.py
wrapdll/tests/test_wraped_kernel32.py
wrapdll/tests/test_wraped_python_api.py
wrapdll/tests/wraped_kernel32.py
wrapdll/tests/wraped_python_api.py